{
  "strategies": [
    {
      "id": "dalembert_1y",
      "name": "[1年 -18%] 连3单押双 爬楼梯",
      "desc": "信号:连续 3 期开单 → 押双。爬楼梯下注:起步 = 当前口袋 // 200 (eg. $2K→$10, $1.6K→$8)。输了 +1 个起步, 赢了 -1 个起步, 最低 1 起步。每次爆仓/翻倍后按新口袋重算起步。回测过去 1 年 (2025-04-29 → 2026-04-28, 146,396 期)。",
      "summary": {
        "strategy_id": "dalembert_1y",
        "start_total": 10000,
        "end_total": 8179,
        "peak_total": 24131,
        "pnl": -1821,
        "pnl_pct": -18.21,
        "peak_pct": 141.31,
        "total_bets": 18204,
        "total_wins": 9137,
        "win_rate": 50.19226543616787,
        "busts": 7,
        "realloc": 1,
        "target_hit": null,
        "current_table": 4807,
        "current_reserve": 3372,
        "days": 365,
        "data_source": "1y",
        "date_start": "2025-04-29",
        "date_end": "2026-04-28",
        "total_draws": 146396
      }
    },
    {
      "id": "dalembert_10y",
      "name": "[10年 破产] 连3单押双 爬楼梯",
      "desc": "同样的策略,回测过去 10 年 (2016-04-29 → 2026-04-28, ~1.46M 期)。10 年订单太多,只保留爆仓/翻倍当天的逐笔订单,其他日子显示当日聚合统计。",
      "summary": {
        "strategy_id": "dalembert_10y",
        "start_total": 10000,
        "end_total": 0,
        "peak_total": 16731,
        "pnl": -10000,
        "pnl_pct": -100.0,
        "peak_pct": 67.31,
        "total_bets": 32258,
        "total_wins": 16157,
        "win_rate": 50.086800173600345,
        "busts": 44,
        "realloc": 0,
        "target_hit": null,
        "current_table": 0,
        "current_reserve": 0,
        "days": 660,
        "data_source": "10y",
        "date_start": "2016-04-29",
        "date_end": "2026-04-28",
        "total_draws": 1434916
      }
    },
    {
      "id": "dalembert_tp_1y",
      "name": "[1年 -96%] 连3单押双 爬楼梯+1%止盈",
      "desc": "同样的信号 (连 3 单押双) 和爬楼梯下注,但加入 1% 止盈重置:口袋从锚点涨够 1% (≥锚点×1.01) → 立刻回到第 1 级,锚点更新为当前口袋,起步按新锚点÷200 重算。频繁锁小利润避免吐回去。回测过去 1 年。",
      "summary": {
        "strategy_id": "dalembert_tp_1y",
        "start_total": 10000,
        "end_total": 443,
        "peak_total": 20000,
        "pnl": -9557,
        "pnl_pct": -95.57,
        "peak_pct": 100.0,
        "total_bets": 18204,
        "total_wins": 9137,
        "win_rate": 50.19226543616787,
        "busts": 21,
        "realloc": 1,
        "target_hit": null,
        "current_table": 153,
        "current_reserve": 290,
        "days": 365,
        "data_source": "1y",
        "date_start": "2025-04-29",
        "date_end": "2026-04-28",
        "total_draws": 146396
      }
    },
    {
      "id": "k7da_xiao80_1y",
      "name": "[1年 +6531% 🚀] 连7大→押小 80%口袋",
      "desc": "信号:连续 7 期开大 → 押当前口袋的 80% (限红 12K)。过去 1 年回测 $10K → $663,088 (+6531%, 66 倍),峰值 $796,288 (80 倍),13 次爆仓。这是从 200+ 个变种暴力搜索出的过去 1 年最强策略。胜率 53.9% (1.7σ 真信号)。",
      "summary": {
        "strategy_id": "k7da_xiao80_1y",
        "start_total": 10000,
        "end_total": 663088,
        "peak_total": 796288,
        "pnl": 653088,
        "pnl_pct": 6530.88,
        "peak_pct": 7862.88,
        "total_bets": 1032,
        "total_wins": 556,
        "win_rate": 53.875968992248055,
        "busts": 13,
        "realloc": 5,
        "target_hit": null,
        "current_table": 254153,
        "current_reserve": 408935,
        "days": 365,
        "data_source": "1y",
        "date_start": "2025-04-29",
        "date_end": "2026-04-28",
        "total_draws": 146396
      }
    },
    {
      "id": "k7da_xiao80_10y",
      "name": "[10年 破产] 连7大→押小 80%口袋",
      "desc": "同样的策略 (连7大→押小 80%口袋),回测过去 10 年 (2016-04-29 → 2026-04-28, ~1.4M 期)。看 10 年级别是否依然能赚或破产。",
      "summary": {
        "strategy_id": "k7da_xiao80_10y",
        "start_total": 10000,
        "end_total": 0,
        "peak_total": 23438,
        "pnl": -10000,
        "pnl_pct": -100.0,
        "peak_pct": 134.38000000000002,
        "total_bets": 609,
        "total_wins": 294,
        "win_rate": 48.275862068965516,
        "busts": 55,
        "realloc": 1,
        "target_hit": null,
        "current_table": 0,
        "current_reserve": 0,
        "days": 187,
        "data_source": "10y",
        "date_start": "2016-04-29",
        "date_end": "2026-04-28",
        "total_draws": 1434916
      }
    },
    {
      "id": "k7da_xiao80_30y",
      "name": "[30年 破产] 连7大→押小 80%口袋",
      "desc": "同样的策略 (连7大→押小 80%口袋),回测过去 30 年完整数据 (1995-11 → 2026-04, ~3.4M 期)。看长期是否能持续盈利,还是只是过去 1 年的 sample lucky。",
      "summary": {
        "strategy_id": "k7da_xiao80_30y",
        "start_total": 10000,
        "end_total": 0,
        "peak_total": 14842,
        "pnl": -10000,
        "pnl_pct": -100.0,
        "peak_pct": 48.42,
        "total_bets": 564,
        "total_wins": 294,
        "win_rate": 52.12765957446809,
        "busts": 43,
        "realloc": 0,
        "target_hit": null,
        "current_table": 0,
        "current_reserve": 0,
        "days": 376,
        "data_source": "30y",
        "date_start": "1995-11-26",
        "date_end": "2026-04-28",
        "total_draws": 3426059
      }
    },
    {
      "id": "k4dan_shuang_1000_10y",
      "name": "[10年 +3094% 🔥极致激进] 连4单→双 $1000",
      "desc": "信号:连续 4 期开单 → 押双 固定 $1000。10 年实测 $10K → $319,368 (+3094%, 年化复利 40.5%),10 次爆仓 + 68% 最大回撤。这是 10 年里 PnL 最高的策略,但波动巨大。",
      "summary": {
        "strategy_id": "k4dan_shuang_1000_10y",
        "start_total": 10000,
        "end_total": 319368,
        "peak_total": 361271,
        "pnl": 309368,
        "pnl_pct": 3093.6800000000003,
        "peak_pct": 3512.71,
        "total_bets": 89478,
        "total_wins": 44960,
        "win_rate": 50.246988086457,
        "busts": 10,
        "realloc": 5,
        "target_hit": null,
        "current_table": 207841,
        "current_reserve": 111527,
        "days": 3652,
        "data_source": "10y",
        "date_start": "2016-04-29",
        "date_end": "2026-04-28",
        "total_draws": 1434916
      }
    },
    {
      "id": "k12da_xiao_5000_10y",
      "name": "[10年 +2490% 💼中等] 连12大→小 $5000",
      "desc": "信号:连续 12 期开大 → 押小 固定 $5000。10 年实测 $10K → $258,973 (+2490%, 年化 38.6%),3 次爆仓 + 33% 回撤。信号低频 (~28 次/年),但单注大,综合稳健。",
      "summary": {
        "strategy_id": "k12da_xiao_5000_10y",
        "start_total": 10000,
        "end_total": 258973,
        "peak_total": 273973,
        "pnl": 248973,
        "pnl_pct": 2489.73,
        "peak_pct": 2639.73,
        "total_bets": 279,
        "total_wins": 165,
        "win_rate": 59.13978494623656,
        "busts": 3,
        "realloc": 4,
        "target_hit": null,
        "current_table": 107314,
        "current_reserve": 151659,
        "days": 3652,
        "data_source": "10y",
        "date_start": "2016-04-29",
        "date_end": "2026-04-28",
        "total_draws": 1434916
      }
    },
    {
      "id": "k12da_xiao_1500_10y",
      "name": "[10年 +743% 🛡️稳健0爆仓] 连12大→小 $1500",
      "desc": "信号:连续 12 期开大 → 押小 固定 $1500。10 年实测 $10K → $84,340 (+743%, 年化 23.7% 跟巴菲特持平),**0 次爆仓** + 24.6% 回撤。0 爆仓中 PnL 最高的策略。",
      "summary": {
        "strategy_id": "k12da_xiao_1500_10y",
        "start_total": 10000,
        "end_total": 84340,
        "peak_total": 88840,
        "pnl": 74340,
        "pnl_pct": 743.4,
        "peak_pct": 788.4000000000001,
        "total_bets": 279,
        "total_wins": 165,
        "win_rate": 59.13978494623656,
        "busts": 0,
        "realloc": 3,
        "target_hit": null,
        "current_table": 17948,
        "current_reserve": 66392,
        "days": 3652,
        "data_source": "10y",
        "date_start": "2016-04-29",
        "date_end": "2026-04-28",
        "total_draws": 1434916
      }
    },
    {
      "id": "k4dan_dalembert_1y",
      "name": "[1年 +220%] 连4单→押双 胜负路爬楼梯",
      "desc": "信号:连续 4 期开单 → 下一期押双。胜负路爬楼梯:起步 = 口袋÷200 (eg. $2K→$10),押双输了 +1 个起步,押双赢了 -1 个起步,最低回到 1 个起步。每个连4单触发只下 1 期。爆仓/翻倍后 level 重置回 1,起步按新口袋重算。1 年实测 $10K → $31,958 (+220%),3 爆仓 + 1 翻倍。",
      "summary": {
        "strategy_id": "k4dan_dalembert_1y",
        "start_total": 10000,
        "end_total": 31958,
        "peak_total": 32465,
        "pnl": 21958,
        "pnl_pct": 219.58,
        "peak_pct": 224.65,
        "total_bets": 9067,
        "total_wins": 4620,
        "win_rate": 50.954009043785156,
        "busts": 3,
        "realloc": 1,
        "target_hit": null,
        "current_table": 21714,
        "current_reserve": 10244,
        "days": 365,
        "data_source": "1y",
        "date_start": "2025-04-29",
        "date_end": "2026-04-28",
        "total_draws": 146396
      }
    },
    {
      "id": "k4dan_dalembert_10y",
      "name": "[10年 -54%] 连4单→押双 胜负路爬楼梯",
      "desc": "同样的策略 (连4单押双 + 胜负路爬楼梯),回测过去 10 年 (~1.4M 期)。10 年实测 $10K → $4,606 (-53.9%),40 爆仓 + 4 翻倍,峰值 $178,363。说明这个策略在 10 年级别长期会被磨损,但短期 (过去 1 年) 表现不错。",
      "summary": {
        "strategy_id": "k4dan_dalembert_10y",
        "start_total": 10000,
        "end_total": 4606,
        "peak_total": 178363,
        "pnl": -5394,
        "pnl_pct": -53.94,
        "peak_pct": 1683.63,
        "total_bets": 89478,
        "total_wins": 44960,
        "win_rate": 50.246988086457,
        "busts": 40,
        "realloc": 4,
        "target_hit": null,
        "current_table": 4116,
        "current_reserve": 490,
        "days": 3652,
        "data_source": "10y",
        "date_start": "2016-04-29",
        "date_end": "2026-04-28",
        "total_draws": 1434916
      }
    },
    {
      "id": "k4_4dir_dalembert_1y",
      "name": "[1年 -36%] 恰好连4同色4向 反向胜负路爬楼梯",
      "desc": "触发:恰好连 4 期同色 (= 最近 4 期同色 且 第 5 期不同色)。4 选 1: 连4大→押小 / 连4小→押大 / 连4单→押双 / 连4双→押单,优先级大>小>单>双。胜负路爬楼梯 (起步=口袋÷200, 输+1, 赢-1, 最低 1)。如果押输,streak 延长到 5+ 期不再触发,等 streak 被打断重新形成恰好 4 连才再触发。1 年实测 $10K → $6,424 (-35.8%),9 爆仓 + 0 翻倍。",
      "summary": {
        "strategy_id": "k4_4dir_dalembert_1y",
        "start_total": 10000,
        "end_total": 6424,
        "peak_total": 12151,
        "pnl": -3576,
        "pnl_pct": -35.76,
        "peak_pct": 21.51,
        "total_bets": 17765,
        "total_wins": 8920,
        "win_rate": 50.21108922037715,
        "busts": 9,
        "realloc": 0,
        "target_hit": null,
        "current_table": 5348,
        "current_reserve": 1076,
        "days": 365,
        "data_source": "1y",
        "date_start": "2025-04-29",
        "date_end": "2026-04-28",
        "total_draws": 146396
      }
    },
    {
      "id": "k4_4dir_dalembert_10y",
      "name": "[10年 破产] 恰好连4同色4向 反向胜负路爬楼梯",
      "desc": "同样的策略,回测过去 10 年。10 年实测 $10K → $0 (破产),51 爆仓 + 1 翻倍,峰值 $23,823。修复触发 bug 后的真实长期表现:虽然不会重复触发,但每次触发只下 1 注,d'Alembert 没法在长期克服 -0.15% 抽水。",
      "summary": {
        "strategy_id": "k4_4dir_dalembert_10y",
        "start_total": 10000,
        "end_total": 0,
        "peak_total": 23823,
        "pnl": -10000,
        "pnl_pct": -100.0,
        "peak_pct": 138.23000000000002,
        "total_bets": 34645,
        "total_wins": 17347,
        "win_rate": 50.07071727522009,
        "busts": 51,
        "realloc": 1,
        "target_hit": null,
        "current_table": 0,
        "current_reserve": 0,
        "days": 731,
        "data_source": "10y",
        "date_start": "2016-04-29",
        "date_end": "2026-04-28",
        "total_draws": 1434916
      }
    },
    {
      "id": "k4_4dir_2bet_1y",
      "name": "[1年 -24%] 恰好连4同色4向 反向2注(赢即停) 胜负路爬楼梯",
      "desc": "信号:恰好连 4 期同色 (优先级大>小>单>双)。下注:第 1 注押反向 → 赢则结束 + level-1; 输则 level+1 + 押第 2 注同方向; 第 2 注完成后无论输赢都结束。Session 期间不重新触发。胜负路 d'Alembert level 跨 session 持续。1 年实测 $10K → $7,654 (-23.5%),8 爆仓,峰值 $13,863。",
      "summary": {
        "strategy_id": "k4_4dir_2bet_1y",
        "start_total": 10000,
        "end_total": 7654,
        "peak_total": 13863,
        "pnl": -2346,
        "pnl_pct": -23.46,
        "peak_pct": 38.629999999999995,
        "total_bets": 25724,
        "total_wins": 12977,
        "win_rate": 50.44705333540662,
        "busts": 8,
        "realloc": 0,
        "target_hit": null,
        "current_table": 6310,
        "current_reserve": 1344,
        "days": 365,
        "data_source": "1y",
        "date_start": "2025-04-29",
        "date_end": "2026-04-28",
        "total_draws": 146396
      }
    },
    {
      "id": "k4_4dir_2bet_10y",
      "name": "[10年 破产] 恰好连4同色4向 反向2注(赢即停) 胜负路爬楼梯",
      "desc": "同样策略,回测过去 10 年。10 年实测 $10K → $0 (破产),45 爆仓,峰值 $10,722。",
      "summary": {
        "strategy_id": "k4_4dir_2bet_10y",
        "start_total": 10000,
        "end_total": 0,
        "peak_total": 10722,
        "pnl": -10000,
        "pnl_pct": -100.0,
        "peak_pct": 7.22,
        "total_bets": 31521,
        "total_wins": 15819,
        "win_rate": 50.185590558675166,
        "busts": 45,
        "realloc": 0,
        "target_hit": null,
        "current_table": 0,
        "current_reserve": 0,
        "days": 458,
        "data_source": "10y",
        "date_start": "2016-04-29",
        "date_end": "2026-04-28",
        "total_draws": 1434916
      }
    },
    {
      "id": "iso3_dalembert_1y",
      "name": "[1年 破产] 3孤立大押小/3孤立小押大 持续押+胜负路爬楼梯",
      "desc": "计数器:大计数从最近大大之后开始数(单个孤立大+1, 大大→清零, 类似), 小计数同理。任一 >= 3 进入对应押注 (3孤立大→押小, 3孤立小→押大),直到对应方向出现双(大大/小小)退出。大优先。胜负路 d'Alembert (起步=口袋÷200, 输+1, 赢-1, 共享 level)。期间每期都押。1 年实测 $10K → $0 (破产),49 爆仓,胜率 49.94%。",
      "summary": {
        "strategy_id": "iso3_dalembert_1y",
        "start_total": 10000,
        "end_total": 0,
        "peak_total": 10915,
        "pnl": -10000,
        "pnl_pct": -100.0,
        "peak_pct": 9.15,
        "total_bets": 12978,
        "total_wins": 6481,
        "win_rate": 49.938357219910614,
        "busts": 49,
        "realloc": 0,
        "target_hit": null,
        "current_table": 0,
        "current_reserve": 0,
        "days": 141,
        "data_source": "1y",
        "date_start": "2025-04-29",
        "date_end": "2026-04-28",
        "total_draws": 146396
      }
    },
    {
      "id": "iso3_dalembert_10y",
      "name": "[10年 破产] 3孤立大押小/3孤立小押大 持续押+胜负路爬楼梯",
      "desc": "同样策略,回测过去 10 年。10 年实测 $10K → $0 (破产),45 爆仓,胜率 49.84%。",
      "summary": {
        "strategy_id": "iso3_dalembert_10y",
        "start_total": 10000,
        "end_total": 0,
        "peak_total": 16468,
        "pnl": -10000,
        "pnl_pct": -100.0,
        "peak_pct": 64.68,
        "total_bets": 55623,
        "total_wins": 27720,
        "win_rate": 49.83549970336012,
        "busts": 45,
        "realloc": 0,
        "target_hit": null,
        "current_table": 0,
        "current_reserve": 0,
        "days": 608,
        "data_source": "10y",
        "date_start": "2016-04-29",
        "date_end": "2026-04-28",
        "total_draws": 1434916
      }
    }
  ],
  "framework": {
    "start_total": 10000,
    "table_ratio": "1/5",
    "reserve_ratio": "4/5",
    "target": 1000000,
    "max_bet": 12000,
    "rules_summary": "起始 $10K → 口袋 $2K + 备用金 $8K。爆仓 → 拿剩余 1/5 当新口袋。总额 ≥ 锚点×2 → 重新分配 (1/5 + 4/5)。达 $1M 停手。"
  }
}